wonka-0.1.5.dist-info/METADATA
wonka-0.1.5.dist-info/WHEEL
wonka-0.1.5.dist-info/entry_points.txt
wonka-0.1.5.dist-info/licenses/LICENSE
wonka/__init__.py
wonka/base.py
wonka/configuration.py
wonka/dispatchers.py
wonka/managers.py
wonka/producers.py
wonka/prototypers.py
wonka/registries.py
wonka/shared.py
wonka/storage.py
wonka/utilities.py
wonka-0.1.5.dist-info/RECORD
