Metadata-Version: 2.1
Name: wonka
Version: 0.1.5
Summary: Flexible, accessible, extensible Python factories
Keywords: factory,construction,constructor,design pattern
Author-Email: Corey Rayburn Yung <coreyrayburnyung@gmail.com>
License: Apache Software License 2.0
Classifier: Development Status :: 4 - Beta
Classifier: Intended Audience :: Developers
Classifier: Programming Language :: Python
Classifier: Programming Language :: Python :: 3
Classifier: Programming Language :: Python :: 3 :: Only
Classifier: Programming Language :: Python :: 3.11
Classifier: Programming Language :: Python :: 3.12
Classifier: Topic :: Software Development
Classifier: Topic :: Utilities
Project-URL: Documentation, https://WithPrecedent.github.io/wonka
Project-URL: Repository, https://github.com/WithPrecedent/wonka
Project-URL: Issues, https://github.com/WithPrecedent/wonka/issues
Project-URL: Changelog, https://WithPrecedent.github.io/wonka/changelog
Requires-Python: >=3.11
